rag/__init__.py
rag/constants.py
rag/dataset_loader.py
rag/rag.py
rag/retriever.py
rag/vectorizer.py
test/__init__.py
test/test_dataset_loader.py
test/test_rag.py
test/test_retriever.py
test/test_vectorizer.py
SimpleRAGHuggingFace-0.1.0.dist-info/METADATA
SimpleRAGHuggingFace-0.1.0.dist-info/WHEEL
SimpleRAGHuggingFace-0.1.0.dist-info/top_level.txt
SimpleRAGHuggingFace-0.1.0.dist-info/RECORD
