Metadata-Version: 2.2
Name: SimpleRAGHuggingFace
Version: 0.1.0
Summary: A simple Retrieval-Augmented Generation (RAG) library using Hugging Face datasets.
Home-page: https://github.com/julianVelandia/SimpleRAGHuggingFace
Author: Julian Camilo Velandia
Author-email: velandiagutierrez@gmail.com
Classifier: Programming Language :: Python :: 3
Classifier: License :: OSI Approved :: MIT License
Classifier: Operating System :: OS Independent
Requires-Python: >=3.7
Requires-Dist: datasets>=2.0.0
Requires-Dist: scikit-learn>=1.0.0
Requires-Dist: numpy>=1.20.0
Dynamic: author
Dynamic: author-email
Dynamic: classifier
Dynamic: description
Dynamic: description-content-type
Dynamic: home-page
Dynamic: requires-dist
Dynamic: requires-python
Dynamic: summary
